owotext/__init__.py
owotext/owo.py
owotext-1.1.1.dist-info/LICENSE
owotext-1.1.1.dist-info/METADATA
owotext-1.1.1.dist-info/WHEEL
owotext-1.1.1.dist-info/entry_points.txt
owotext-1.1.1.dist-info/top_level.txt
owotext-1.1.1.dist-info/RECORD
