Metadata-Version: 2.1
Name: owotext
Version: 1.1.1
Summary: A Python library for converting text strings into OwO
Home-page: https://github.com/DerpyChap/owotext
Author: DerpyChap
Author-email: holla@derpychap.co.uk
License: MIT
Platform: UNKNOWN
